pyslop/cronslator/__init__.py
pyslop/cronslator/cli.py
pyslop/cronslator/cronslator.py
pyslop_cronslator-0.2.3.dist-info/LICENSE
pyslop_cronslator-0.2.3.dist-info/METADATA
pyslop_cronslator-0.2.3.dist-info/WHEEL
pyslop_cronslator-0.2.3.dist-info/entry_points.txt
pyslop_cronslator-0.2.3.dist-info/RECORD
