Metadata-Version: 2.1
Name: pyslop-cronslator
Version: 0.2.3
Summary: Natural Language to Cron
Home-page: https://github.com/pyslop/cronslator
License: CC0-1.0
Keywords: cron,natural language,schedule,translator
Author: Harshad Sharma
Author-email: harshad@sharma.io
Requires-Python: >=3.9,<4.0
Classifier: License :: CC0 1.0 Universal (CC0 1.0) Public Domain Dedication
Classifier: Programming Language :: Python :: 3
Classifier: Programming Language :: Python :: 3.9
Classifier: Programming Language :: Python :: 3.10
Classifier: Programming Language :: Python :: 3.11
Classifier: Programming Language :: Python :: 3.12
Classifier: Programming Language :: Python :: 3.13
